{
  "name": "example",
  "styles": [
    {
      "keyword": "default_style",
      "layerGroup": "Bubbles",
      "fontName": "CCComicrazy-Roman",
      "size": 25,
      "leading": 0,
      "tracking": 0,
      "vScale": 100,
      "hScale": 100,
      "capitalization": "NORMAL",
      "justification": "CENTER",
      "antialias": "SMOOTH",
      "fauxBold": false,
      "fauxItalic": false,
      "hyphenate": true,
      "kerning": "METRICS",
      "default": true,
      "languages": "englishLanguage",
      "textOrientation": "HORIZONTAL"
    },
    {
      "keyword": "handwritten",
      "layerGroup": "Bubbles",
      "fontName": "MDBurnette",
      "size": 25,
      "leading": 0,
      "tracking": 0,
      "vScale": 100,
      "hScale": 100,
      "capitalization": "NORMAL",
      "justification": "CENTER",
      "antialias": "SMOOTH",
      "fauxBold": false,
      "fauxItalic": false,
      "hyphenate": true,
      "kerning": "METRICS",
      "languages": "englishLanguage",
      "textOrientation": "HORIZONTAL"
    },
    {
      "keyword": "italic",
      "layerGroup": "Bubbles",
      "fontName": "Arial-ItalicMT",
      "size": 25,
      "leading": 0,
      "tracking": 0,
      "vScale": 100,
      "hScale": 100,
      "capitalization": "NORMAL",
      "justification": "CENTER",
      "antialias": "SMOOTH",
      "fauxBold": false,
      "fauxItalic": false,
      "hyphenate": true,
      "kerning": "METRICS",
      "languages": "englishLanguage",
      "textOrientation": "HORIZONTAL"
    },
    {
      "keyword": "japanese_style",
      "layerGroup": "Asian stuff",
      "fontName": "Osaka",
      "size": 25,
      "leading": 0,
      "tracking": 0,
      "vScale": 100,
      "hScale": 100,
      "capitalization": "NORMAL",
      "justification": "LEFT",
      "antialias": "SMOOTH",
      "fauxBold": false,
      "fauxItalic": false,
      "hyphenate": true,
      "kerning": "METRICS",
      "languages": "englishLanguage",
      "textOrientation": "VERTICAL"
    },
    {
      "keyword": "newspaper",
      "layerGroup": "Others",
      "fontName": "ElectraLTStd-Regular",
      "size": 25,
      "leading": 0,
      "tracking": 0,
      "vScale": 100,
      "hScale": 100,
      "capitalization": "NORMAL",
      "justification": "CENTER",
      "antialias": "SMOOTH",
      "fauxBold": false,
      "fauxItalic": false,
      "hyphenate": true,
      "kerning": "METRICS",
      "languages": "englishLanguage",
      "textOrientation": "HORIZONTAL"
    },
    {
      "keyword": "nib",
      "layerGroup": "Bubbles",
      "fontName": "CCComicrazy-Italic",
      "size": 25,
      "leading": 0,
      "tracking": 0,
      "vScale": 100,
      "hScale": 100,
      "capitalization": "NORMAL",
      "justification": "CENTER",
      "antialias": "SMOOTH",
      "fauxBold": false,
      "fauxItalic": false,
      "hyphenate": true,
      "kerning": "METRICS",
      "languages": "englishLanguage",
      "textOrientation": "HORIZONTAL"
    },
    {
      "keyword": "other_style",
      "layerGroup": "Others",
      "fontName": "BitchCakes",
      "size": 25,
      "leading": 0,
      "tracking": 0,
      "vScale": 100,
      "hScale": 100,
      "capitalization": "NORMAL",
      "justification": "CENTER",
      "antialias": "SMOOTH",
      "fauxBold": false,
      "fauxItalic": false,
      "hyphenate": true,
      "kerning": "METRICS",
      "languages": "englishLanguage",
      "textOrientation": "HORIZONTAL"
    },
    {
      "keyword": "sfx",
      "layerGroup": "SFXs",
      "fontName": "AdamWarrenpro",
      "size": 25,
      "leading": 0,
      "tracking": 0,
      "vScale": 100,
      "hScale": 100,
      "capitalization": "NORMAL",
      "justification": "CENTER",
      "antialias": "SMOOTH",
      "fauxBold": false,
      "fauxItalic": false,
      "hyphenate": true,
      "kerning": "METRICS",
      "languages": "englishLanguage",
      "textOrientation": "HORIZONTAL"
    },
    {
      "keyword": "sfxib",
      "layerGroup": null,
      "fontName": "Another",
      "size": 25,
      "leading": 0,
      "tracking": 0,
      "vScale": 100,
      "hScale": 100,
      "capitalization": "NORMAL",
      "justification": "CENTER",
      "antialias": "SMOOTH",
      "fauxBold": false,
      "fauxItalic": false,
      "hyphenate": true,
      "kerning": "METRICS",
      "languages": "englishLanguage",
      "textOrientation": "HORIZONTAL"
    },
    {
      "keyword": "yelling",
      "layerGroup": "SFXs",
      "fontName": "CCComicrazy-BoldItalic",
      "size": 25,
      "leading": 0,
      "tracking": 0,
      "vScale": 100,
      "hScale": 100,
      "capitalization": "NORMAL",
      "justification": "CENTER",
      "antialias": "SMOOTH",
      "fauxBold": false,
      "fauxItalic": false,
      "hyphenate": true,
      "kerning": "METRICS",
      "languages": "englishLanguage",
      "textOrientation": "HORIZONTAL"
    }
  ],
  "language": "englishLanguage"
}